[{"name": "sb", "value": "TBMwaCBe8W5acOdjA5-k2XO_", "domain": ".facebook.com", "path": "/", "secure": true, "httpOnly": true}, {"name": "wd", "value": "1440x812", "domain": ".facebook.com", "path": "/", "secure": true, "httpOnly": true}, {"name": "datr", "value": "TBMwaN8JYOdidWdXwRyK6yaJ", "domain": ".facebook.com", "path": "/", "secure": true, "httpOnly": true}, {"name": "ps_l", "value": "1", "domain": ".facebook.com", "path": "/", "secure": true, "httpOnly": true}, {"name": "ps_n", "value": "1", "domain": ".facebook.com", "path": "/", "secure": true, "httpOnly": true}, {"name": "c_user", "value": "100010893247259", "domain": ".facebook.com", "path": "/", "secure": true, "httpOnly": true}, {"name": "xs", "value": "29%3AWfzDpBfmHcx2xQ%3A2%3A1747981139%3A-1%3A-1", "domain": ".facebook.com", "path": "/", "secure": true, "httpOnly": true}, {"name": "fr", "value": "1jI09I8yHGTT0C5Cc.AWcvP1k9NXHZ5fxzAgJej61AXO319oHUeHCr2SQM543lDLTWNLI.BoMAXl..AAA.0.0.BoMBNW.AWcoTlVDRyoXMQtOYGfwe_tI8eY", "domain": ".facebook.com", "path": "/", "secure": true, "httpOnly": true}, {"name": "presence", "value": "C%7B%22t3%22%3A%5B%5D%2C%22utc3%22%3A1747981144204%2C%22v%22%3A1%7D", "domain": ".facebook.com", "path": "/", "secure": true, "httpOnly": true}]